{"id":"64ba4028245ac9c0d17c2c5c","title":"Ma Đinh","origin_name":"Hellraiser","slug":"ma-dinh","thumb":"https://cdn.jsdelivr.net/gh/gotvtop102/goimg102@main/public/thumbs/ma/ma-dinh.webp","poster":"https://cdn.jsdelivr.net/gh/gotvtop102/goimg102@main/public/posters/ma/ma-dinh.webp","year":"1987","type":"single","genre":[{"name":"Kinh Dị","slug":"kinh-di"},{"name":"Bí ẩn","slug":"bi-an"}],"country":[{"name":"Âu Mỹ","slug":"au-my"}],"lang_key":"Vietsub","episode_current":"Full","quality":"HD","modified":"2023-07-21T15:22:03.000Z","is_4k":false,"is_exclusive":false,"status":"completed","showtimes":"","chieurap":false,"sub_docquyen":false,"episodes":[{"name":"Vietsub #1","slug":"vietsub-1","server_name":"Vietsub #1","server_data":[{"name":"Full","slug":"full","link_embed":"https://vip.opstream14.com/share/a7bcf3bc23946c7d69a73acb147ca8e8","link_m3u8":"https://vip.opstream14.com/20230721/38698_e433c771/index.m3u8"}]}],"description":"Sau khi mày mò với chiếc hộp anh mua khi ở nước ngoài, Frank lệch lạc tình dục đã vô tình mở ra cánh cổng dẫn đến địa ngục, nơi những con quỷ tôn sùng do Pinhead cầm đầu xé nát cơ thể anh. Khi anh trai của Frank và vợ của anh ta chuyển đến nhà của anh ta, một bộ xương Frank xuất hiện với chị dâu của anh ta và yêu cầu cô ta cung cấp xác chết cho anh ta để anh ta tái sinh.","tmdb_id":9003,"cast":[],"director":[],"keywords":[],"tmdb":{"id":9003},"cast_meta":[],"tmdb_checked":false,"pubjs_url":"https://cdn.jsdelivr.net/gh/gotvtop102/pjs102@main/pubjs/ma/ma-dinh.json"}