{"id":"691fe9f1fe926797f4970429","title":"Gặp Millie Black","origin_name":"Get Millie Black","slug":"gap-millie-black","thumb":"https://cdn.jsdelivr.net/gh/phantruongngoc102/goimg102@main/public/thumbs/ga/gap-millie-black.webp","poster":"https://cdn.jsdelivr.net/gh/phantruongngoc102/goimg102@main/public/posters/ga/gap-millie-black.webp","year":2024,"type":"series","genre":[{"id":"620a2249e0fc277084dfd2e5","name":"Hình Sự","slug":"hinh-su"},{"id":"620f3d2b91fa4af90ab697fe","name":"Chính kịch","slug":"chinh-kich"}],"country":[{"id":"620a231fe0fc277084dfd7ce","name":"Âu Mỹ","slug":"au-my"},{"id":"620a2370e0fc277084dfd91e","name":"Anh","slug":"anh"}],"lang_key":"Vietsub","episode_current":"Hoàn Tất (5/5)","quality":"HD","is_4k":false,"is_exclusive":false,"status":"completed","showtimes":"","chieurap":false,"sub_docquyen":false,"episodes":[{"server_name":"Vietsub #1","is_ai":false,"server_data":[{"name":"1","slug":"1","filename":"Gặp Millie Black - Tập 1","link_embed":"https://vip.opstream17.com/share/ae6a757b965961ebbec156a82c5c9f40","link_m3u8":"https://vip.opstream17.com/20251119/22844_ae6a757b/index.m3u8"},{"name":"2","slug":"2","filename":"Gặp Millie Black - Tập 2","link_embed":"https://vip.opstream17.com/share/8e5687e2d6ab87e5da2f833f3e8986a4","link_m3u8":"https://vip.opstream17.com/20251119/22845_8e5687e2/index.m3u8"},{"name":"3","slug":"3","filename":"Gặp Millie Black - Tập 3","link_embed":"https://vip.opstream17.com/share/49f925ccf67d449d8ca3ad8b5b8fea76","link_m3u8":"https://vip.opstream17.com/20251119/22846_49f925cc/index.m3u8"},{"name":"4","slug":"4","filename":"Gặp Millie Black - Tập 4","link_embed":"https://vip.opstream17.com/share/2872ff9b142a5511d445ed927cd24332","link_m3u8":"https://vip.opstream17.com/20251119/22847_2872ff9b/index.m3u8"},{"name":"5","slug":"5","filename":"Gặp Millie Black - Tập 5","link_embed":"https://vip.opstream17.com/share/26f7fe7e89bce7ecb6112bad5d5efeeb","link_m3u8":"https://vip.opstream17.com/20251119/22848_26f7fe7e/index.m3u8"}]}],"time":"63 phút/tập","description":"<p>Cựu thám tử Scotland Yard Millie-Jean Black trở lại Kingston để điều tra những người mất tích; cô sớm nhận ra mình đang trên đường giải cứu một người chị gái không thể cứu được, tìm một cậu bé không thể tìm thấy, giải quyết một vụ án sẽ làm đảo lộn thế giới của cô và chứng tỏ rằng việc giải quyết nó cũng khó khăn như Millie Black.</p>","tmdb":{"type":"tv","id":"201646","season":1,"vote_average":6.233,"vote_count":43},"modified":"2025-11-21T11:26:28.000Z","cast":["Tamara Lawrance","Joe Dempsie","Gershwyn Eustache Jnr","Chyna McQueen","Christopher Daley","Shernet Swearine","Belinda Reid","Peter John Thwaites"],"director":[],"cast_meta":[{"name":"Tamara Lawrance","name_vi":null,"name_original":"Tamara Lawrance","tmdb_id":1595457,"profile":"https://image.tmdb.org/t/p/w500/dxmaQIEhFVwOhU1f6vTV06CU2Jj.jpg","tmdb_url":"https://www.themoviedb.org/person/1595457"},{"name":"Joe Dempsie","name_vi":null,"name_original":"Joe Dempsie","tmdb_id":570296,"profile":"https://image.tmdb.org/t/p/w500/47XNLVxbLsEBFgGYgbHAIYE5ja9.jpg","tmdb_url":"https://www.themoviedb.org/person/570296"},{"name":"Gershwyn Eustache Jnr","name_vi":null,"name_original":"Gershwyn Eustache Jnr","tmdb_id":1192778,"profile":"https://image.tmdb.org/t/p/w500/gxlb7XbcvSU0fBrlbM0z5pO7leY.jpg","tmdb_url":"https://www.themoviedb.org/person/1192778"},{"name":"Chyna McQueen","name_vi":null,"name_original":"Chyna McQueen","tmdb_id":3543284,"profile":"https://image.tmdb.org/t/p/w500/6WZqeERDmM8P9bLW1rMSiWnW5Nj.jpg","tmdb_url":"https://www.themoviedb.org/person/3543284"},{"name":"Christopher Daley","name_vi":null,"name_original":"Christopher Daley","tmdb_id":4097463,"profile":null,"tmdb_url":"https://www.themoviedb.org/person/4097463"},{"name":"Shernet Swearine","name_vi":null,"name_original":"Shernet Swearine","tmdb_id":5167286,"profile":null,"tmdb_url":"https://www.themoviedb.org/person/5167286"},{"name":"Belinda Reid","name_vi":null,"name_original":"Belinda Reid","tmdb_id":5167287,"profile":null,"tmdb_url":"https://www.themoviedb.org/person/5167287"},{"name":"Peter John Thwaites","name_vi":null,"name_original":"Peter John Thwaites","tmdb_id":5167289,"profile":null,"tmdb_url":"https://www.themoviedb.org/person/5167289"}],"keywords":[],"tmdb_checked":true,"pubjs_url":"https://cdn.jsdelivr.net/gh/phantruongngoc102/pjs102@main/pubjs/ga/gap-millie-black.json"}