{"id":"69dc729ba54286c41ba3f3b3","title":"The Anacondas","origin_name":"The Anacondas","slug":"the-anacondas","thumb":"https://cdn.jsdelivr.net/gh/phantruongngoc102/goimg102@main/public/thumbs/th/the-anacondas.webp","poster":"https://cdn.jsdelivr.net/gh/phantruongngoc102/goimg102@main/public/posters/th/the-anacondas.webp","year":2025,"type":"single","genre":[{"id":"620a21b2e0fc277084dfd0c5","name":"Hành Động","slug":"hanh-dong"},{"id":"620a2293e0fc277084dfd489","name":"Phiêu Lưu","slug":"phieu-luu"},{"id":"620a22ace0fc277084dfd531","name":"Kinh Dị","slug":"kinh-di"}],"country":[{"id":"620a231fe0fc277084dfd7ce","name":"Âu Mỹ","slug":"au-my"}],"lang_key":"Vietsub","episode_current":"Full","quality":"HD","is_4k":false,"is_exclusive":false,"status":"completed","showtimes":"","chieurap":false,"sub_docquyen":false,"episodes":[{"server_name":"Vietsub #1","is_ai":false,"server_data":[{"name":"Full","slug":"full","filename":"(Sub Viet  AI) The.Anacondas.2025.FANSUB.VOSTFR.1080p.WEB-DL.H.264-Slay3R","link_embed":"https://vip.opstream12.com/share/08ecfbbc924a19234f7eb081c20d87ac","link_m3u8":"https://vip.opstream12.com/20260414/32653_08ecfbbc/index.m3u8"}]}],"time":"90 Phút","description":"<p>Các nhà thám hiểm ở Mexico đã phát hiện ra tàn tích của một nền văn minh cổ đại thờ rắn. Niềm vui biến thành nỗi kinh hoàng khi họ đánh thức một con trăn khổng lồ không ngừng lớn lên, con vật đã bị bỏ đói vì thiếu lễ vật hiến tế người trong nhiều thế kỷ. Giờ đây, cả nhóm phải đoàn kết để sống sót.</p>","tmdb":{"type":"movie","id":"1595325","season":null,"vote_average":4.5,"vote_count":6},"modified":"2026-04-15T15:28:14.000Z","cast":["Hannah Hueston","Jordan Iverach","Philipp Karner","Dominic Keating","Maureen Kedes","Bix Krieger","Giselle Garci","Marcus Mannis","Brian Russell","Danielle Titus","Andrew Tong","Michael James Vargas"],"director":["Marcel Walz"],"cast_meta":[{"name":"Hannah Hueston","name_vi":null,"name_original":"Hannah Hueston","tmdb_id":2896531,"profile":"https://image.tmdb.org/t/p/w500/wc48icP82y3WoI37w3gqBWNUbiQ.jpg","tmdb_url":"https://www.themoviedb.org/person/2896531"},{"name":"Jordan Iverach","name_vi":null,"name_original":"Jordan Iverach","tmdb_id":5865503,"profile":null,"tmdb_url":"https://www.themoviedb.org/person/5865503"},{"name":"Philipp Karner","name_vi":null,"name_original":"Philipp Karner","tmdb_id":1212104,"profile":"https://image.tmdb.org/t/p/w500/ubw2BP4sxr2EOnATeG7O7jG2bx5.jpg","tmdb_url":"https://www.themoviedb.org/person/1212104"},{"name":"Dominic Keating","name_vi":null,"name_original":"Dominic Keating","tmdb_id":23790,"profile":"https://image.tmdb.org/t/p/w500/eRe4BJz9fTztlRKikDRHhmss6ee.jpg","tmdb_url":"https://www.themoviedb.org/person/23790"},{"name":"Maureen Kedes","name_vi":null,"name_original":"Maureen Kedes","tmdb_id":163503,"profile":"https://image.tmdb.org/t/p/w500/vWhGJCC2QXDe6S15dbXjdRAc9yJ.jpg","tmdb_url":"https://www.themoviedb.org/person/163503"},{"name":"Bix Krieger","name_vi":null,"name_original":"Bix Krieger","tmdb_id":4479427,"profile":"https://image.tmdb.org/t/p/w500/xrNatpwrSauF3MsmWLviG18rNW0.jpg","tmdb_url":"https://www.themoviedb.org/person/4479427"},{"name":"Giselle Garci","name_vi":null,"name_original":"Giselle Garci","tmdb_id":5865554,"profile":"https://image.tmdb.org/t/p/w500/wjFIMmDjMs0EaPl23DAx1BKJGhS.jpg","tmdb_url":"https://www.themoviedb.org/person/5865554"},{"name":"Marcus Mannis","name_vi":null,"name_original":"Marcus Mannis","tmdb_id":5865559,"profile":null,"tmdb_url":"https://www.themoviedb.org/person/5865559"},{"name":"Brian Russell","name_vi":null,"name_original":"Brian Russell","tmdb_id":3260687,"profile":null,"tmdb_url":"https://www.themoviedb.org/person/3260687"},{"name":"Danielle Titus","name_vi":null,"name_original":"Danielle Titus","tmdb_id":5426462,"profile":"https://image.tmdb.org/t/p/w500/oDs3OlALCKuwlI5B2imBaPDzt7H.jpg","tmdb_url":"https://www.themoviedb.org/person/5426462"},{"name":"Andrew Tong","name_vi":null,"name_original":"Andrew Tong","tmdb_id":5865561,"profile":null,"tmdb_url":"https://www.themoviedb.org/person/5865561"},{"name":"Michael James Vargas","name_vi":null,"name_original":"Michael James Vargas","tmdb_id":5865562,"profile":null,"tmdb_url":"https://www.themoviedb.org/person/5865562"}],"keywords":["snake"],"tmdb_checked":true,"pubjs_url":"https://cdn.jsdelivr.net/gh/phantruongngoc102/pjs102@main/pubjs/th/the-anacondas.json"}