{"id":"626c7b743a2c0c6289b869f6","title":"StartUp (Phần 2)","origin_name":"StartUp (Season 2)","slug":"startup-phan-2","thumb":"https://cdn.jsdelivr.net/gh/gotvtop102/goimg102@main/public/thumbs/st/startup-phan-2.webp","poster":"https://cdn.jsdelivr.net/gh/gotvtop102/goimg102@main/public/posters/st/startup-phan-2.webp","year":2017,"type":"series","genre":[{"id":"620a2238e0fc277084dfd291","name":"Tâm Lý","slug":"tam-ly"},{"id":"620f3d2b91fa4af90ab697fe","name":"Chính kịch","slug":"chinh-kich"}],"country":[{"id":"620a231fe0fc277084dfd7ce","name":"Âu Mỹ","slug":"au-my"}],"lang_key":"Vietsub","episode_current":"Hoàn Tất (10/10)","quality":"HD","is_4k":false,"is_exclusive":false,"status":"completed","showtimes":"","chieurap":false,"sub_docquyen":false,"episodes":[{"server_name":"Vietsub #1","is_ai":false,"server_data":[{"name":"1","slug":"1","filename":"StartUp_S02E01_Phá vỡ","link_embed":"https://vip.opstream16.com/share/10fa5eb83300e5f592b9b35a0e07fc3f","link_m3u8":"https://vip.opstream16.com/20220427/10033_3984623c/index.m3u8"},{"name":"2","slug":"2","filename":"StartUp_S02E02_Tối tân","link_embed":"https://vip.opstream16.com/share/b2fb19fe374529d3658197da0657ab0c","link_m3u8":"https://vip.opstream16.com/20220427/10034_c31aef5c/index.m3u8"},{"name":"3","slug":"3","filename":"StartUp_S02E03_Nhóm khách hàng thích nghi nhanh","link_embed":"https://vip.opstream16.com/share/329d1ea6acb272924f991d523b2d2b80","link_m3u8":"https://vip.opstream16.com/20220427/10035_5ff1e432/index.m3u8"},{"name":"4","slug":"4","filename":"StartUp_S02E04_Thua lỗ","link_embed":"https://vip.opstream16.com/share/7c127e0c66f06e58c7c7310a7c6fa488","link_m3u8":"https://vip.opstream16.com/20220427/10036_d46e28bd/index.m3u8"},{"name":"5","slug":"5","filename":"StartUp_S02E05_Mấu chốt","link_embed":"https://vip.opstream16.com/share/4ccea3161064506dda8e0c9fd416d1ae","link_m3u8":"https://vip.opstream16.com/20220427/10037_86be62e0/index.m3u8"},{"name":"6","slug":"6","filename":"StartUp_S02E06_Nghĩa vụ","link_embed":"https://vip.opstream16.com/share/0f6b1f657ac30ab76519ed4c677e9909","link_m3u8":"https://vip.opstream16.com/20220427/10038_6f9a2115/index.m3u8"},{"name":"7","slug":"7","filename":"StartUp_S02E07_Marketing đột phá","link_embed":"https://vip.opstream16.com/share/2a8009525763356ad5e3bb48b7475b4d","link_m3u8":"https://vip.opstream16.com/20220427/10039_842dcd65/index.m3u8"},{"name":"8","slug":"8","filename":"StartUp_S02E08_Chi phí cơ hội","link_embed":"https://vip.opstream16.com/share/f250daff6a09865ff432821b2adac54f","link_m3u8":"https://vip.opstream16.com/20220427/10040_3852dd4a/index.m3u8"},{"name":"9","slug":"9","filename":"StartUp_S02E09_Đòn bẩy","link_embed":"https://vip.opstream16.com/share/6d38b80c1da3bd9d8717ce47fea2acd7","link_m3u8":"https://vip.opstream16.com/20220427/10041_924a8896/index.m3u8"},{"name":"10","slug":"10","filename":"StartUp_S02E10_Chủ sở hữu linh hồn","link_embed":"https://vip.opstream16.com/share/425f116bf53f051c57d1670a04fb4a0c","link_m3u8":"https://vip.opstream16.com/20220427/10042_fdad816a/index.m3u8"}]}],"time":"54phút/tập","description":"<p>Với GenCoin hiện nằm trong tay băng đảng người Nga, các cộng sự Izzy, Ronald và Nick bắt đầu một dự án mạng ngầm mới cũng nguy hiểm không kém.</p>","tmdb":{"type":"tv","id":"66310","season":2,"vote_average":7.189,"vote_count":244},"modified":"2023-06-12T14:25:19.000Z","cast":["Adam Brody","Edi Gathegi","Otmara Marrero","Addison Timlin","Ron Perlman","Mira Sorvino"],"director":[],"cast_meta":[{"name":"Adam Brody","name_vi":null,"name_original":"Adam Brody","tmdb_id":11702,"profile":"https://image.tmdb.org/t/p/w500/qKBWrohBYegm6AAaLrtxEqqouIK.jpg","tmdb_url":"https://www.themoviedb.org/person/11702"},{"name":"Edi Gathegi","name_vi":null,"name_original":"Edi Gathegi","tmdb_id":39391,"profile":"https://image.tmdb.org/t/p/w500/dt8yMyycDlzxkjhmuuJJ4tXDbp4.jpg","tmdb_url":"https://www.themoviedb.org/person/39391"},{"name":"Otmara Marrero","name_vi":null,"name_original":"Otmara Marrero","tmdb_id":1608786,"profile":"https://image.tmdb.org/t/p/w500/n9x3D82mzFopkiVJpOPNrgF0B1H.jpg","tmdb_url":"https://www.themoviedb.org/person/1608786"},{"name":"Addison Timlin","name_vi":null,"name_original":"Addison Timlin","tmdb_id":56542,"profile":"https://image.tmdb.org/t/p/w500/ropQg0oZZP0R3xkWxYNdMx8glHi.jpg","tmdb_url":"https://www.themoviedb.org/person/56542"},{"name":"Ron Perlman","name_vi":null,"name_original":"Ron Perlman","tmdb_id":2372,"profile":"https://image.tmdb.org/t/p/w500/pOgMRdJhbBsvwGLRFXPRASTfcay.jpg","tmdb_url":"https://www.themoviedb.org/person/2372"},{"name":"Mira Sorvino","name_vi":null,"name_original":"Mira Sorvino","tmdb_id":23931,"profile":"https://image.tmdb.org/t/p/w500/3CPM8yvppihiKsA1pf4x8PJe4x6.jpg","tmdb_url":"https://www.themoviedb.org/person/23931"}],"keywords":[],"tmdb_checked":true,"pubjs_url":"https://cdn.jsdelivr.net/gh/gotvtop102/pjs102@main/pubjs/st/startup-phan-2.json"}