{"id":"62a9fada7a956fb5db126b1f","title":"8 con người ở Istanbul","origin_name":"Ethos","slug":"8-con-nguoi-o-istanbul","thumb":"https://cdn.jsdelivr.net/gh/gotvtop102/goimg102@main/public/thumbs/8_/8-con-nguoi-o-istanbul.webp","poster":"https://cdn.jsdelivr.net/gh/gotvtop102/goimg102@main/public/posters/8_/8-con-nguoi-o-istanbul.webp","year":"2020","type":"series","genre":[{"name":"Chính kịch","slug":"chinh-kich"}],"country":[{"name":"Thổ Nhĩ Kỳ","slug":"tho-nhi-ky"}],"lang_key":"Vietsub","episode_current":"Hoàn Tất (8/8)","quality":"HD","modified":"2022-06-15T15:29:30.000Z","is_4k":false,"is_exclusive":false,"status":"completed","showtimes":"","chieurap":false,"sub_docquyen":false,"episodes":[{"name":"Vietsub #1","slug":"vietsub-1","server_name":"Vietsub #1","server_data":[{"name":"1","slug":"1","link_embed":"https://vip.opstream15.com/share/cf655665801fc01205314e121a0ee8c2","link_m3u8":"https://vip.opstream15.com/20220615/20845_0a2d7768/index.m3u8"},{"name":"2","slug":"2","link_embed":"https://vip.opstream15.com/share/d3036eaa59b31dade3e8ef4916a3e821","link_m3u8":"https://vip.opstream15.com/20220615/20849_da570a0d/index.m3u8"},{"name":"3","slug":"3","link_embed":"https://vip.opstream15.com/share/a6df0bdb9111011bb923c11b2bc2e5fd","link_m3u8":"https://vip.opstream15.com/20220615/20853_e34ce291/index.m3u8"},{"name":"4","slug":"4","link_embed":"https://vip.opstream15.com/share/afa5b2e548f3d4a647ee75ec79bc60cd","link_m3u8":"https://vip.opstream15.com/20220615/20857_d860adc0/index.m3u8"},{"name":"5","slug":"5","link_embed":"https://vip.opstream15.com/share/57902633a9b75c60dd351cd33856950b","link_m3u8":"https://vip.opstream15.com/20220615/20858_51b84f78/index.m3u8"},{"name":"6","slug":"6","link_embed":"https://vip.opstream15.com/share/98908fce27744e259d6b7d7bb87de294","link_m3u8":"https://vip.opstream15.com/20220615/20866_96e5039e/index.m3u8"},{"name":"7","slug":"7","link_embed":"https://vip.opstream15.com/share/6c2cce23c4449723bdce7208c1e1dc5e","link_m3u8":"https://vip.opstream15.com/20220615/20872_3c37f6c7/index.m3u8"},{"name":"8","slug":"8","link_embed":"https://vip.opstream15.com/share/b6084866846db24332059399de7d6b97","link_m3u8":"https://vip.opstream15.com/20220615/20877_1be9515e/index.m3u8"}]}],"description":"<p>Một nhóm người ở Istanbul vượt qua những rào cản văn hóa xã hội và tìm được sự kết nối khi những sợ hãi và ước muốn của họ đan xen.</p>","tmdb_id":112745,"cast":["Öykü Karayel","Funda Eryiğit","Fatih Artman","Defne Kayalar","Tülin Özen","Alican Yücesoy","Settar Tanrıöğen"],"director":["Berkun Oya"],"keywords":[],"cast_meta":[{"name":"Öykü Karayel","name_vi":null,"name_original":"Öykü Karayel","tmdb_id":1255433,"profile":"https://image.tmdb.org/t/p/w500/rzMUT2OMgnlsDLKUIdPDM0q2mgf.jpg","tmdb_url":"https://www.themoviedb.org/person/1255433"},{"name":"Funda Eryiğit","name_vi":null,"name_original":"Funda Eryiğit","tmdb_id":1059109,"profile":"https://image.tmdb.org/t/p/w500/gS2Hh173nIRYeSljkOL8UhTWClS.jpg","tmdb_url":"https://www.themoviedb.org/person/1059109"},{"name":"Fatih Artman","name_vi":null,"name_original":"Fatih Artman","tmdb_id":1254540,"profile":"https://image.tmdb.org/t/p/w500/xCzXSuy7JZ418Yb0x6FR6pf2p3J.jpg","tmdb_url":"https://www.themoviedb.org/person/1254540"},{"name":"Defne Kayalar","name_vi":null,"name_original":"Defne Kayalar","tmdb_id":1893085,"profile":"https://image.tmdb.org/t/p/w500/fAgk8WrdfnNxVbu764XDTuEPWAq.jpg","tmdb_url":"https://www.themoviedb.org/person/1893085"},{"name":"Tülin Özen","name_vi":null,"name_original":"Tülin Özen","tmdb_id":130400,"profile":"https://image.tmdb.org/t/p/w500/pXCnJDfwo6yW8aYXpg8ZeJHvJIm.jpg","tmdb_url":"https://www.themoviedb.org/person/130400"},{"name":"Alican Yücesoy","name_vi":null,"name_original":"Alican Yücesoy","tmdb_id":930674,"profile":"https://image.tmdb.org/t/p/w500/3IrUq0Mo2oWKgzmSfIplOE7X0ro.jpg","tmdb_url":"https://www.themoviedb.org/person/930674"},{"name":"Settar Tanrıöğen","name_vi":null,"name_original":"Settar Tanrıöğen","tmdb_id":40024,"profile":"https://image.tmdb.org/t/p/w500/zgVuK1f31l6TakyhsF59FzFahP0.jpg","tmdb_url":"https://www.themoviedb.org/person/40024"}],"tmdb_checked":true,"tmdb":{"id":112745},"pubjs_url":"https://cdn.jsdelivr.net/gh/gotvtop102/pjs102@main/pubjs/8_/8-con-nguoi-o-istanbul.json"}