{"id":"6821c071a0ec502ff3a03bf6","title":"Tình Yêu C4","origin_name":"C4 Cinta","slug":"tinh-yen-c4","thumb":"https://cdn.jsdelivr.net/gh/phantruongngoc102/goimg102@main/public/thumbs/ti/tinh-yen-c4.webp","poster":"https://cdn.jsdelivr.net/gh/phantruongngoc102/goimg102@main/public/posters/ti/tinh-yen-c4.webp","year":2024,"type":"single","genre":[{"id":"620a221de0fc277084dfd1c1","name":"Hài Hước","slug":"hai-huoc"}],"country":[{"id":"62159af71f1609c9d934824e","name":"Malaysia","slug":"malaysia"}],"lang_key":"Vietsub","episode_current":"Full","quality":"HD","is_4k":false,"is_exclusive":false,"status":"completed","showtimes":"","chieurap":false,"sub_docquyen":false,"episodes":[{"server_name":"Vietsub #1","is_ai":false,"server_data":[{"name":"Full","slug":"full","filename":"Tình yêu C4","link_embed":"https://vip.opstream90.com/share/4b85256c4881edb6c0776df5d81f6236","link_m3u8":"https://vip.opstream90.com/20250512/5503_4b85256c/index.m3u8"}]}],"time":"167 Phút","description":"<p>Bộ phim liên kết nhiều cốt truyện đan xen cuộc sống của Hari, Soniya và những người bạn của họ, khi họ điều hướng sự phức tạp của các mối quan hệ được hàn gắn lại và những sự thật không được nói ra trên khắp các vùng đất sôi động của Singapore và Malaysia. Khi họ đối mặt với quá khứ và hiện tại của mình, bộ phim khám phá các chủ đề về tình yêu, ký ức và bản sắc. Hành trình của mỗi nhân vật được kết nối chặt chẽ, mang đến một bức tranh phong phú về kịch tính cảm xúc, giá trị gia đình và tình bạn.</p>","tmdb":{"type":"movie","id":"1390963","season":null,"vote_average":0,"vote_count":0},"modified":"2025-05-12T16:43:42.000Z","cast":["Yuvaraj Krishnasamy","Pashini Sivakumar","Loga Varman Strideran","Ravin Rao Santeran","K. S. Maniam","Thia Lakshana"],"director":["Karthik Shamalan"],"cast_meta":[{"name":"Yuvaraj Krishnasamy","name_vi":null,"name_original":"Yuvaraj Krishnasamy","tmdb_id":2108302,"profile":null,"tmdb_url":"https://www.themoviedb.org/person/2108302"},{"name":"Pashini Sivakumar","name_vi":null,"name_original":"Pashini Sivakumar","tmdb_id":2080643,"profile":null,"tmdb_url":"https://www.themoviedb.org/person/2080643"},{"name":"Loga Varman Strideran","name_vi":null,"name_original":"Loga Varman Strideran","tmdb_id":3815294,"profile":null,"tmdb_url":"https://www.themoviedb.org/person/3815294"},{"name":"Ravin Rao Santeran","name_vi":null,"name_original":"Ravin Rao Santeran","tmdb_id":4049973,"profile":null,"tmdb_url":"https://www.themoviedb.org/person/4049973"},{"name":"K. S. Maniam","name_vi":null,"name_original":"K. S. Maniam","tmdb_id":1284845,"profile":null,"tmdb_url":"https://www.themoviedb.org/person/1284845"},{"name":"Thia Lakshana","name_vi":null,"name_original":"Thia Lakshana","tmdb_id":3815295,"profile":null,"tmdb_url":"https://www.themoviedb.org/person/3815295"}],"keywords":["tamil","c4cinta"],"tmdb_checked":true,"pubjs_url":"https://cdn.jsdelivr.net/gh/phantruongngoc102/pjs102@main/pubjs/ti/tinh-yen-c4.json"}