{"id":"62be9bee9464119c3457f056","title":"Cô Nàng Xinh Đẹp Và Cặp Song Sinh","origin_name":"Different Taste: Very Different Twin Brothers","slug":"co-nang-xinh-dep-va-cap-song-sinh","thumb":"https://cdn.jsdelivr.net/gh/phantruongngoc102/goimg102@main/public/thumbs/co/co-nang-xinh-dep-va-cap-song-sinh.webp","poster":"https://cdn.jsdelivr.net/gh/phantruongngoc102/goimg102@main/public/posters/co/co-nang-xinh-dep-va-cap-song-sinh.webp","year":2020,"type":"single","genre":[{"id":"6242b89cc78eb57bbfe29f91","name":"Phim 18+","slug":"phim-18"}],"country":[{"id":"620a2300e0fc277084dfd6d2","name":"Hàn Quốc","slug":"han-quoc"}],"lang_key":"Vietsub","episode_current":"Full","quality":"HD","is_4k":false,"is_exclusive":false,"status":"completed","showtimes":"","chieurap":false,"sub_docquyen":true,"episodes":[{"is_ai":false,"server_name":"Vietsub #1","server_data":[{"name":"Full","slug":"full","filename":"co-nang-sinh-dep-va-cap-song-sinh-muxed","link_embed":"https://vip.opstream14.com/share/bd6c2fd1ded9513bc167f856167cf5dc","link_m3u8":"https://vip.opstream14.com/20220701/16634_4d36a090/index.m3u8"}]}],"time":"93 phút","description":"<p>Ri-na được bạn trai Geun-ho tặng một chiếc quần lót, nhưng cô thấy nó có kích thước quá khác biệt. Trong khi đợi Geun-ho trước nhà của anh ấy, cô ấy tìm thấy Geun-ho và lẻn vào nhà với Yoo-min và chứng kiến mối quan hệ không tốt giữa hai người. Ri-na bị sốc trước sự thay đổi 180 độ của Geun-ho so với cô, nhưng sau đó cô phát hiện ra rằng đó chính là anh trai sinh đôi của anh Jae-ho, chứ không phải Geun-ho. Tuy nhiên, Ri-na đã nghe được tin tức bất ngờ từ Yoo-min rằng Jae-ho thực sự là Geun-ho, và khi được đề nghị chia tay, cô ấy đã thú nhận với Geun-ho rằng cô ấy muốn có một mối quan hệ với Yoo-min.</p>","tmdb":{"type":null,"id":"","season":null,"vote_average":0,"vote_count":0},"modified":"2023-04-10T13:32:06.000Z","cast":["Joo Ah-I","Min Do-yoon","Sae Bom-I","Sang Woo","So Jeong"],"director":["Yoon Gyeong-sik"],"cast_meta":[{"name":"Joo Ah-I","name_vi":null,"name_original":"Joo Ah-I"},{"name":"Min Do-yoon","name_vi":null,"name_original":"Min Do-yoon"},{"name":"Sae Bom-I","name_vi":null,"name_original":"Sae Bom-I"},{"name":"Sang Woo","name_vi":null,"name_original":"Sang Woo"},{"name":"So Jeong","name_vi":null,"name_original":"So Jeong"}],"pubjs_url":"https://cdn.jsdelivr.net/gh/phantruongngoc102/pjs102@main/pubjs/co/co-nang-xinh-dep-va-cap-song-sinh.json","keywords":[],"tmdb_checked":false}