{"id":"6218e5e4a2d0f024a9de4782","title":"Code Geass: Lelouch nổi loạn – Bộ ba phim","origin_name":"Code Geass: Lelouch of the Rebellion - Movie Trilogy","slug":"code-geass-lelouch-noi-loan-bo-ba-phim","thumb":"https://cdn.jsdelivr.net/gh/gotvtop102/goimg102@main/public/thumbs/co/code-geass-lelouch-noi-loan-bo-ba-phim.webp","poster":"https://cdn.jsdelivr.net/gh/gotvtop102/goimg102@main/public/posters/co/code-geass-lelouch-noi-loan-bo-ba-phim.webp","year":"2017","type":"hoathinh","genre":[{"name":"Hành Động","slug":"hanh-dong"},{"name":"Viễn Tưởng","slug":"vien-tuong"},{"name":"Phiêu Lưu","slug":"phieu-luu"},{"name":"Khoa Học","slug":"khoa-hoc"}],"country":[{"name":"Nhật Bản","slug":"nhat-ban"}],"lang_key":"Vietsub","episode_current":"Hoàn tất (03/03)","quality":"HD","modified":"2023-08-09T10:10:54.000Z","is_4k":false,"is_exclusive":false,"status":"completed","showtimes":"","chieurap":false,"sub_docquyen":false,"episodes":[{"name":"Vietsub #1","slug":"vietsub-1","server_name":"Vietsub #1","server_data":[{"name":"Hưng Đạo","slug":"hung-dao","link_embed":"https://vip.opstream15.com/share/38af86134b65d0f10fe33d30dd76442e","link_m3u8":"https://vip.opstream15.com/20220225/176_e2ecb99f/index.m3u8"},{"name":"Phản Đạo","slug":"phan-dao","link_embed":"https://vip.opstream15.com/share/8f85517967795eeef66c225f7883bdcb","link_m3u8":"https://vip.opstream15.com/20220225/178_6457cf0a/index.m3u8"},{"name":"Hoàng Đạo","slug":"hoang-dao","link_embed":"https://vip.opstream15.com/share/045117b0e0a11a242b9765e79cbf113f","link_m3u8":"https://vip.opstream15.com/20220225/180_c40521eb/index.m3u8"}]}],"description":"<p>Khi chiến tranh chia cắt hai anh em khỏi gia đình hoàng tộc tàn ác, vị hoàng tử thâm hiểm đã tự tay lo chuyện ngoại giao. Phim là phiên bản mới của loạt phim kinh điển.</p>","tmdb_id":null,"cast":[],"director":[],"keywords":[],"cast_meta":[],"pubjs_url":"https://cdn.jsdelivr.net/gh/gotvtop102/pjs102@main/pubjs/co/code-geass-lelouch-noi-loan-bo-ba-phim.json"}