{"id":"69c0ee25124287e08263fb53","title":"Goddess of Love","origin_name":"Goddess of Love","slug":"goddess-of-love","thumb":"https://cdn.jsdelivr.net/gh/gotvtop102/goimg102@main/public/thumbs/go/goddess-of-love.webp","poster":"https://cdn.jsdelivr.net/gh/gotvtop102/goimg102@main/public/posters/go/goddess-of-love.webp","year":2015,"type":"single","genre":[{"id":"620a22ace0fc277084dfd531","name":"Kinh Dị","slug":"kinh-di"},{"id":"620f3d2b91fa4af90ab697fe","name":"Chính kịch","slug":"chinh-kich"},{"id":"620f84d291fa4af90ab6b3f4","name":"Bí ẩn","slug":"bi-an"}],"country":[{"id":"620a231fe0fc277084dfd7ce","name":"Âu Mỹ","slug":"au-my"},{"id":"620a2381e0fc277084dfd9c6","name":"Canada","slug":"canada"}],"lang_key":"Vietsub","episode_current":"Full","quality":"HD","is_4k":false,"is_exclusive":false,"status":"completed","showtimes":"","chieurap":false,"sub_docquyen":false,"episodes":[{"server_name":"Vietsub #1","is_ai":false,"server_data":[{"name":"Full","slug":"full","filename":"(Sub Viet AI) Goddess.of.Love.2015.1080p.BluRay.x264-OFT","link_embed":"https://vip.opstream12.com/share/555ed9de909ff98b3a9de74ed0be9ecf","link_m3u8":"https://vip.opstream12.com/20260324/32608_555ed9de/index.m3u8"}]}],"time":"96 Phút","description":"<p>Bước vào vòng xoáy điên loạn đầy màu sắc khi một người phụ nữ bất ổn về mặt cảm xúc bị suy sụp sau nỗi đau khổ tột cùng. Brian là tình yêu của đời Venus, và ý nghĩ anh ta ngoại tình với người phụ nữ khác đã khởi đầu cho sự sa sút không kiểm soát của cô vào mặt tối của chứng điên loạn tâm thần tình dục.</p>","tmdb":{"type":"movie","id":"347764","season":null,"vote_average":5.278,"vote_count":45},"modified":"2026-03-25T10:00:38.000Z","cast":["Alexis Kendra","Elizabeth Sandy","Monda Scott","Woody Naismith","Ray Grady","Richard Velton","Hugh Westbourne","Rachel Alig","Deana Ricks","Anna Logan","Kendall Foote"],"director":["Jon Knautz"],"cast_meta":[{"name":"Alexis Kendra","name_vi":null,"name_original":"Alexis Kendra","tmdb_id":566796,"profile":"https://image.tmdb.org/t/p/w500/hygpp2m8QNckBkfuozhpI7qZnSg.jpg","tmdb_url":"https://www.themoviedb.org/person/566796"},{"name":"Elizabeth Sandy","name_vi":null,"name_original":"Elizabeth Sandy","tmdb_id":932030,"profile":"https://image.tmdb.org/t/p/w500/hDRRrwUbwE7JiTwlsV3MXIhlROX.jpg","tmdb_url":"https://www.themoviedb.org/person/932030"},{"name":"Monda Scott","name_vi":null,"name_original":"Monda Scott","tmdb_id":1485125,"profile":"https://image.tmdb.org/t/p/w500/yrkF0YDT7G4iK3JBfH9NhQYQRv2.jpg","tmdb_url":"https://www.themoviedb.org/person/1485125"},{"name":"Woody Naismith","name_vi":null,"name_original":"Woody Naismith","tmdb_id":62491,"profile":null,"tmdb_url":"https://www.themoviedb.org/person/62491"},{"name":"Ray Grady","name_vi":null,"name_original":"Ray Grady","tmdb_id":1322802,"profile":"https://image.tmdb.org/t/p/w500/jXMOwMIKJyvX0UTBqALhE4CZyy.jpg","tmdb_url":"https://www.themoviedb.org/person/1322802"},{"name":"Richard Velton","name_vi":null,"name_original":"Richard Velton","tmdb_id":1573359,"profile":null,"tmdb_url":"https://www.themoviedb.org/person/1573359"},{"name":"Hugh Westbourne","name_vi":null,"name_original":"Hugh Westbourne","tmdb_id":1573360,"profile":null,"tmdb_url":"https://www.themoviedb.org/person/1573360"},{"name":"Rachel Alig","name_vi":null,"name_original":"Rachel Alig","tmdb_id":1059001,"profile":"https://image.tmdb.org/t/p/w500/rvD8pcQufVLWX4LGVuGsFmrdcC4.jpg","tmdb_url":"https://www.themoviedb.org/person/1059001"},{"name":"Deana Ricks","name_vi":null,"name_original":"Deana Ricks","tmdb_id":1654871,"profile":null,"tmdb_url":"https://www.themoviedb.org/person/1654871"},{"name":"Anna Logan","name_vi":null,"name_original":"Anna Logan","tmdb_id":3241328,"profile":null,"tmdb_url":"https://www.themoviedb.org/person/3241328"},{"name":"Kendall Foote","name_vi":null,"name_original":"Kendall Foote","tmdb_id":3038971,"profile":null,"tmdb_url":"https://www.themoviedb.org/person/3038971"}],"keywords":[],"tmdb_checked":true,"pubjs_url":"https://cdn.jsdelivr.net/gh/gotvtop102/pjs102@main/pubjs/go/goddess-of-love.json"}