{"id":"66790367213d9187e980e80f","title":"Xác Sống Đáng Sợ (Phần 3)","origin_name":"Fear the Walking Dead (Season 3)","slug":"khoi-nguon-xac-song-phan-3","thumb":"https://cdn.jsdelivr.net/gh/gotvtop102/goimg102@main/public/thumbs/kh/khoi-nguon-xac-song-phan-3.webp","poster":"https://cdn.jsdelivr.net/gh/gotvtop102/goimg102@main/public/posters/kh/khoi-nguon-xac-song-phan-3.webp","year":"2017","type":"series","genre":[{"name":"Hành Động","slug":"hanh-dong"},{"name":"Phiêu Lưu","slug":"phieu-luu"},{"name":"Chính kịch","slug":"chinh-kich"}],"country":[{"name":"Âu Mỹ","slug":"au-my"}],"lang_key":"Vietsub","episode_current":"Hoàn Tất (16/16)","quality":"HD","modified":"2024-06-24T12:55:02.000Z","is_4k":false,"is_exclusive":false,"status":"completed","showtimes":"","chieurap":false,"sub_docquyen":false,"episodes":[{"name":"Vietsub #1","slug":"vietsub-1","server_name":"Vietsub #1","server_data":[{"name":"1","slug":"1","link_embed":"https://vip.opstream17.com/share/8ad124e01f97c4cf812b49a875fc0965","link_m3u8":"https://vip.opstream17.com/20240623/12963_8c809d60/index.m3u8"},{"name":"2","slug":"2","link_embed":"https://vip.opstream17.com/share/412bb949b10ebe6b9fe743385388f3cb","link_m3u8":"https://vip.opstream17.com/20240623/12964_d2b3eaee/index.m3u8"},{"name":"3","slug":"3","link_embed":"https://vip.opstream17.com/share/c0410c653460d525550e95c900d6b644","link_m3u8":"https://vip.opstream17.com/20240623/12965_f70234f7/index.m3u8"},{"name":"4","slug":"4","link_embed":"https://vip.opstream17.com/share/4fd31a77f882ecb871a3f0fb44e1a4d0","link_m3u8":"https://vip.opstream17.com/20240623/12966_f286f3ba/index.m3u8"},{"name":"5","slug":"5","link_embed":"https://vip.opstream17.com/share/5e2474f1e2b6e1e2a6985974062b664c","link_m3u8":"https://vip.opstream17.com/20240623/12967_5e4a797f/index.m3u8"},{"name":"6","slug":"6","link_embed":"https://vip.opstream17.com/share/78c784cf4f1360d2c590de5146e67b4c","link_m3u8":"https://vip.opstream17.com/20240623/12968_a3fdc201/index.m3u8"},{"name":"7","slug":"7","link_embed":"https://vip.opstream17.com/share/4cbb466a35d3bb7304ea43cd687929f0","link_m3u8":"https://vip.opstream17.com/20240623/12969_9e785674/index.m3u8"},{"name":"8","slug":"8","link_embed":"https://vip.opstream17.com/share/b1d3a8fba2c3b1a07da18922ec3d5664","link_m3u8":"https://vip.opstream17.com/20240623/12970_78d4df99/index.m3u8"},{"name":"9","slug":"9","link_embed":"https://vip.opstream17.com/share/9bb9852b78e55603158ed65149db7dd6","link_m3u8":"https://vip.opstream17.com/20240623/12971_c77c5683/index.m3u8"},{"name":"10","slug":"10","link_embed":"https://vip.opstream17.com/share/c1f22f4c38899f51f1ed3ce20120bbd9","link_m3u8":"https://vip.opstream17.com/20240623/12972_a064e259/index.m3u8"},{"name":"11","slug":"11","link_embed":"https://vip.opstream17.com/share/4fbd11aeadd719c8cf9c6d501b854755","link_m3u8":"https://vip.opstream17.com/20240623/12973_ac85aa73/index.m3u8"},{"name":"12","slug":"12","link_embed":"https://vip.opstream17.com/share/293643def1ba1161bcdcfbfe434ab76d","link_m3u8":"https://vip.opstream17.com/20240623/12974_c2eae9ac/index.m3u8"},{"name":"13","slug":"13","link_embed":"https://vip.opstream17.com/share/3b63d1d64de8f499eadb49b53aa90964","link_m3u8":"https://vip.opstream17.com/20240623/12975_9509943a/index.m3u8"},{"name":"14","slug":"14","link_embed":"https://vip.opstream17.com/share/2e36742b377be90ffbf553692153d9a1","link_m3u8":"https://vip.opstream17.com/20240623/12976_9f7c1bfe/index.m3u8"},{"name":"15","slug":"15","link_embed":"https://vip.opstream17.com/share/001b8e3cf76f4e64cbe5be9882db4aa0","link_m3u8":"https://vip.opstream17.com/20240623/12977_75076985/index.m3u8"},{"name":"16","slug":"16","link_embed":"https://vip.opstream17.com/share/950d4aea25553820c10d71160da80944","link_m3u8":"https://vip.opstream17.com/20240623/12978_dae46e02/index.m3u8"}]}],"description":"<p>Các gia đình sẽ được đoàn tụ tại khu vực sôi động và bạo lực trước đây được gọi là biên giới Mỹ-Mexico. Các đường lối quốc tế bị loại bỏ sau ngày tận thế, các nhân vật của chúng ta phải cố gắng xây dựng lại không chỉ xã hội mà cả gia đình.</p>","tmdb_id":62286,"cast":["Lennie James","Kim Dickens","Colman Domingo","Danay García","Austin Amelio","Karen David","Christine Evangelista","Daniel Sharman","Jenna Elfman","Rubén Blades"],"director":[],"keywords":[],"tmdb":{"type":"tv","id":"62286","season":3,"vote_average":7.631,"vote_count":5118},"cast_meta":[{"name":"Lennie James","name_vi":null,"name_original":"Lennie James","tmdb_id":1120,"profile":"https://image.tmdb.org/t/p/w500/lUcouck90jXNzyJr5uBJJiYMHAN.jpg","tmdb_url":"https://www.themoviedb.org/person/1120"},{"name":"Kim Dickens","name_vi":null,"name_original":"Kim Dickens","tmdb_id":21165,"profile":"https://image.tmdb.org/t/p/w500/yr6kstI1hdLP6LXz2xyBB4ovduj.jpg","tmdb_url":"https://www.themoviedb.org/person/21165"},{"name":"Colman Domingo","name_vi":null,"name_original":"Colman Domingo","tmdb_id":91671,"profile":"https://image.tmdb.org/t/p/w500/2tu6T9ugnf82qIMGVKWSb0dvvq5.jpg","tmdb_url":"https://www.themoviedb.org/person/91671"},{"name":"Danay García","name_vi":null,"name_original":"Danay García","tmdb_id":1225996,"profile":"https://image.tmdb.org/t/p/w500/iS4vwXHoPhOdwUQS7J9kplitvlh.jpg","tmdb_url":"https://www.themoviedb.org/person/1225996"},{"name":"Austin Amelio","name_vi":null,"name_original":"Austin Amelio","tmdb_id":1552436,"profile":"https://image.tmdb.org/t/p/w500/y4QTXuSSmD99n8dinMiTRBkUnAp.jpg","tmdb_url":"https://www.themoviedb.org/person/1552436"},{"name":"Karen David","name_vi":null,"name_original":"Karen David","tmdb_id":79124,"profile":"https://image.tmdb.org/t/p/w500/zi4fUbrhvXqufdR4Ws7WflNUGLs.jpg","tmdb_url":"https://www.themoviedb.org/person/79124"},{"name":"Christine Evangelista","name_vi":null,"name_original":"Christine Evangelista","tmdb_id":208160,"profile":"https://image.tmdb.org/t/p/w500/1ceQNIpOmpcpEH8rvY0SIQBzg0G.jpg","tmdb_url":"https://www.themoviedb.org/person/208160"},{"name":"Daniel Sharman","name_vi":null,"name_original":"Daniel Sharman","tmdb_id":119248,"profile":"https://image.tmdb.org/t/p/w500/8ESi3BUMWmFlxs1LmybHd4PF76j.jpg","tmdb_url":"https://www.themoviedb.org/person/119248"},{"name":"Jenna Elfman","name_vi":null,"name_original":"Jenna Elfman","tmdb_id":40279,"profile":"https://image.tmdb.org/t/p/w500/AsXlf2XtVF3tyx0GrUPRq72NLIa.jpg","tmdb_url":"https://www.themoviedb.org/person/40279"},{"name":"Rubén Blades","name_vi":null,"name_original":"Rubén Blades","tmdb_id":2049,"profile":"https://image.tmdb.org/t/p/w500/kOgVo3qDJ9jXgIZJRJI3I1bm6sA.jpg","tmdb_url":"https://www.themoviedb.org/person/2049"}],"tmdb_checked":true,"pubjs_url":"https://cdn.jsdelivr.net/gh/gotvtop102/pjs102@main/pubjs/kh/khoi-nguon-xac-song-phan-3.json"}